aparatpy/__init__.py
aparatpy/exceptions.py
aparatpy/main.py
aparatpy/scraper.py
aparatpy-3.1.1.dist-info/LICENSE
aparatpy-3.1.1.dist-info/METADATA
aparatpy-3.1.1.dist-info/WHEEL
aparatpy-3.1.1.dist-info/top_level.txt
aparatpy-3.1.1.dist-info/RECORD
