Metadata-Version: 2.1
Name: aparatpy
Version: 3.1.1
Summary: aparat.com downloader
Home-page: https://github.com/dori-dev/aparatpy
Author: Mohammad Dori
Author-email: mr.dori.dev@gmail.com
License: UNKNOWN
Platform: UNKNOWN
Classifier: Programming Language :: Python :: 3
Classifier: License :: OSI Approved :: MIT License
Classifier: Operating System :: OS Independent
Requires-Python: >=3.6
License-File: LICENSE
Requires-Dist: requests
Requires-Dist: beautifulsoup4
